siDynoReader/__init__.py
siDynoReader/sidynoreader.py
tests/__init__.py
tests/test.py
sidynoreader-0.1.5.dist-info/METADATA
sidynoreader-0.1.5.dist-info/WHEEL
sidynoreader-0.1.5.dist-info/top_level.txt
sidynoreader-0.1.5.dist-info/RECORD
