Metadata-Version: 2.1
Name: sidynoreader
Version: 0.1.5
Summary: UNKNOWN
Home-page: UNKNOWN
License: UNKNOWN
Platform: UNKNOWN
Requires-Dist: numpy==2.0.2
